cli/__init__.py
cli/cli.py
cli/setup.py
anthropic_cli-0.2.0.dist-info/METADATA
anthropic_cli-0.2.0.dist-info/WHEEL
anthropic_cli-0.2.0.dist-info/entry_points.txt
anthropic_cli-0.2.0.dist-info/top_level.txt
anthropic_cli-0.2.0.dist-info/RECORD
