Metadata-Version: 2.1
Name: anthropic-cli
Version: 0.2.0
Summary: A command-line tool for interacting with the Anthropic API
Author-email: David Mohl <git@d.sh>
Project-URL: Homepage, https://github.com/dvcrn/anthropic-cli
Project-URL: Bug Tracker, https://github.com/dvcrn/anthropic-cli/issues
Keywords: anthropic,api,cli,command-line
Classifier: Development Status :: 3 - Alpha
Classifier: Intended Audience :: Developers
Classifier: License :: OSI Approved :: MIT License
Classifier: Programming Language :: Python :: 3
Classifier: Programming Language :: Python :: 3.7
Classifier: Programming Language :: Python :: 3.8
Classifier: Programming Language :: Python :: 3.9
Classifier: Programming Language :: Python :: 3.10
Classifier: Programming Language :: Python :: 3.11
Requires-Python: >=3.7
